statcert/__init__.py
statcert/__main__.py
statcert/cli/__init__.py
statcert/cli/inputs.py
statcert/cli/main.py
statcert/cli/options.py
statcert/cli/outputs.py
statcert/cli/summary.py
statcert/model/__init__.py
statcert/model/certificate.py
statcert/model/constants.py
statcert/model/info.py
statcert/model/operation.py
statcert/model/record.py
statcert/operation/__init__.py
statcert/operation/asynchttp.py
statcert/operation/ocsp.py
statcert/task_loop.py
statcert-0.0.3.dist-info/entry_points.txt
statcert-0.0.3.dist-info/LICENSE.txt
statcert-0.0.3.dist-info/WHEEL
statcert-0.0.3.dist-info/METADATA
statcert-0.0.3.dist-info/RECORD
